hamu_tool/__init__.py
hamu_tool/dataset/__init__.py
hamu_tool/dataset/data_loader.py
hamu_tool/dataset/data_loader_base.py
hamu_tool/dataset/sparse/__init__.py
hamu_tool/dataset/sparse/beir/__init__.py
hamu_tool/dataset/sparse/beir/data_loader.py
hamu_tool/dataset/sparse/beir/arguana/__init__.py
hamu_tool/dataset/sparse/beir/arguana/data_loader.py
hamu_tool/dataset/sparse/beir/bioasq/__init__.py
hamu_tool/dataset/sparse/beir/bioasq/data_loader.py
hamu_tool/dataset/sparse/beir/climate_fever/__init__.py
hamu_tool/dataset/sparse/beir/climate_fever/data_loader.py
hamu_tool/dataset/sparse/beir/dbpedia/__init__.py
hamu_tool/dataset/sparse/beir/dbpedia/data_loader.py
hamu_tool/dataset/sparse/beir/fever/__init__.py
hamu_tool/dataset/sparse/beir/fever/data_loader.py
hamu_tool/dataset/sparse/beir/fiqa/__init__.py
hamu_tool/dataset/sparse/beir/fiqa/data_loader.py
hamu_tool/dataset/sparse/beir/hotpotqa/__init__.py
hamu_tool/dataset/sparse/beir/hotpotqa/data_loader.py
hamu_tool/dataset/sparse/beir/msmarco/__init__.py
hamu_tool/dataset/sparse/beir/msmarco/data_loader.py
hamu_tool/dataset/sparse/beir/nfcorpus/__init__.py
hamu_tool/dataset/sparse/beir/nfcorpus/data_loader.py
hamu_tool/dataset/sparse/beir/nq/__init__.py
hamu_tool/dataset/sparse/beir/nq/data_loader.py
hamu_tool/dataset/sparse/beir/quora/__init__.py
hamu_tool/dataset/sparse/beir/quora/data_loader.py
hamu_tool/dataset/sparse/beir/robust04/__init__.py
hamu_tool/dataset/sparse/beir/robust04/data_loader.py
hamu_tool/dataset/sparse/beir/scidocs/__init__.py
hamu_tool/dataset/sparse/beir/scidocs/data_loader.py
hamu_tool/dataset/sparse/beir/scifact/__init__.py
hamu_tool/dataset/sparse/beir/scifact/data_loader.py
hamu_tool/dataset/sparse/beir/signal1m/__init__.py
hamu_tool/dataset/sparse/beir/signal1m/data_loader.py
hamu_tool/dataset/sparse/beir/touche/__init__.py
hamu_tool/dataset/sparse/beir/touche/data_loader.py
hamu_tool/dataset/sparse/beir/touche_v2/__init__.py
hamu_tool/dataset/sparse/beir/touche_v2/data_loader.py
hamu_tool-0.0.20.dist-info/METADATA
hamu_tool-0.0.20.dist-info/WHEEL
hamu_tool-0.0.20.dist-info/top_level.txt
hamu_tool-0.0.20.dist-info/RECORD
