Metadata-Version: 2.1
Name: hamu-tool
Version: 0.0.20
Summary: Many useful tools for computer scientists!
Home-page: https://github.com/waylight3/hamu-tool
Author: DoHyeon Lee
Author-email: waylight3@snu.ac.kr
License: MIT
Keywords: hamu,tool,computer,science,useful,toolkit,library,python,package,module,utility,function,class,method
Requires-Python: >=3.11
Requires-Dist: pymupdf
